better_python_lists/__init__.py
better_python_lists/list.py
better_python_lists-0.1.3.dist-info/LICENSE
better_python_lists-0.1.3.dist-info/WHEEL
better_python_lists-0.1.3.dist-info/METADATA
better_python_lists-0.1.3.dist-info/RECORD
