Metadata-Version: 2.1
Name: better-python-lists
Version: 0.1.3
Summary: Adds some useful methods on top of Python lists
License: GNU GENERAL PUBLIC LICENSE v3
Author: Bradley Marques
Author-email: bradleyrcmarques@gmail.com
Requires-Python: >=3.11,<4.0
Classifier: License :: Other/Proprietary License
Classifier: Programming Language :: Python :: 3
Classifier: Programming Language :: Python :: 3.11
